microcache/__init__.py
microcache/_version.py
microcache-1.0.dist-info/LICENSE
microcache-1.0.dist-info/METADATA
microcache-1.0.dist-info/WHEEL
microcache-1.0.dist-info/top_level.txt
microcache-1.0.dist-info/RECORD
